tauth/__init__.py
tauth/__main__.py
tauth/app.py
tauth/settings.py
tauth/authn/__init__.py
tauth/authn/auth0_dyn.py
tauth/authn/routes.py
tauth/authn/tauth_api_key.py
tauth/authn/jwt/__init__.py
tauth/authn/jwt/constants.py
tauth/authn/jwt/credentials.py
tauth/authn/jwt/errors.py
tauth/authn/jwt/keygen.py
tauth/authn/jwt/tokcoder.py
tauth/authn/melt_key/README.md
tauth/authn/melt_key/__init__.py
tauth/authn/melt_key/authentication.py
tauth/authn/melt_key/authorization.py
tauth/authn/melt_key/models.py
tauth/authn/melt_key/schemas.py
tauth/authn/melt_key/token.py
tauth/authproviders/__init__.py
tauth/authproviders/models.py
tauth/authproviders/routes.py
tauth/authproviders/schemas.py
tauth/authz/__init__.py
tauth/authz/privileges.py
tauth/authz/routes.py
tauth/authz/engines/__init__.py
tauth/authz/engines/factory.py
tauth/authz/engines/interface.py
tauth/authz/engines/opa.py
tauth/authz/policies/__init__.py
tauth/authz/policies/controllers.py
tauth/authz/policies/models.py
tauth/authz/policies/routes.py
tauth/authz/policies/schemas.py
tauth/dependencies/__init__.py
tauth/dependencies/authorization.py
tauth/dependencies/cache.py
tauth/dependencies/database.py
tauth/dependencies/security.py
tauth/entities/__init__.py
tauth/entities/models.py
tauth/entities/routes.py
tauth/entities/schemas.py
tauth/injections/__init__.py
tauth/injections/privileges.py
tauth/legacy/__init__.py
tauth/legacy/client.py
tauth/legacy/schemas.py
tauth/legacy/tokens.py
tauth/schemas/__init__.py
tauth/schemas/attribute.py
tauth/schemas/creator.py
tauth/schemas/gen_fields.py
tauth/schemas/infostar.py
tauth/utils/__init__.py
tauth/utils/creation.py
tauth/utils/fastapi_extension.py
tauth/utils/reading.py
tauth/utils/teia_behaviors.py
athena_api-2.0.0.post2.dist-info/LICENSE
athena_api-2.0.0.post2.dist-info/METADATA
athena_api-2.0.0.post2.dist-info/WHEEL
athena_api-2.0.0.post2.dist-info/top_level.txt
athena_api-2.0.0.post2.dist-info/RECORD
